gerepotools/__init__.py
gerepotools/core.py
gerepotools/gejira.py
gerepotools/inoutstream.py
gerepotools/main.py
gerepotools/repo.py
gerepotools/slack.py
gerepotools/version.py
gerepotools/templates/jira_issue.j2
gerepotools/templates/repotools-jira-credential.yml
gerepotools/templates/repotools-jira-target-last.yml
gerepotools/templates/repotools-repo-credential.yml
gerepotools/templates/repotools-repo-target-last.yml
gerepotools/templates/repotools-slack-credential.yml
gerepotools/templates/slack_message.json.j2
gerepotools-1.0.18.dist-info/LICENSE.md
gerepotools-1.0.18.dist-info/METADATA
gerepotools-1.0.18.dist-info/WHEEL
gerepotools-1.0.18.dist-info/entry_points.txt
gerepotools-1.0.18.dist-info/top_level.txt
gerepotools-1.0.18.dist-info/RECORD
