Metadata-Version: 2.1
Name: gerepotools
Version: 1.0.18
Summary: UNKNOWN
Home-page: https://gitlab.com/guichet-entreprises.fr/tools/repo-tools
Author: Arnaud Boidard
Author-email: florent.tournois@gmail.fr
License: MIT
Platform: UNKNOWN
Classifier: Programming Language :: Python
Classifier: Operating System :: OS Independent
Classifier: Programming Language :: Python :: 3
Classifier: Programming Language :: Python :: 3.6
Requires-Dist: repositorytools
Requires-Dist: pyyaml
Requires-Dist: upref
Requires-Dist: jira
Requires-Dist: jinja2
Requires-Dist: brainyquote
Requires-Dist: beautifulsoup4
Requires-Dist: requests
Requires-Dist: slackclient
